pysylph-0.1.2.dist-info/METADATA
pysylph-0.1.2.dist-info/WHEEL
pysylph-0.1.2.dist-info/license_files/COPYING
pysylph/pyfile.rs
pysylph/lib.pyi
pysylph/lib.rs
pysylph/tests/test_database.py
pysylph/tests/k12.R2.fq.gz
pysylph/tests/clodf13.fna.gz
pysylph/tests/o157.sylsp
pysylph/tests/test_sketcher.py
pysylph/tests/__init__.py
pysylph/tests/k12.R1.fq.gz
pysylph/tests/unittest.rs
pysylph/tests/k12.paired.sylsp
pysylph/tests/clodf13.syldb
pysylph/tests/test_profiler.py
pysylph/tests/test_doctest.py
pysylph/tests/ecoli.syldb
pysylph/tests/k12.R1.sylsp
pysylph/__init__.py
pysylph/exports/mod.rs
pysylph/exports/sketch.rs
pysylph/exports/contain.rs
pysylph/py.typed
pysylph/lib.cpython-39-darwin.so
pysylph-0.1.2.dist-info/RECORD
